src/__init__.py
src/main.py
cf_util-1.2.1.dist-info/METADATA
cf_util-1.2.1.dist-info/WHEEL
cf_util-1.2.1.dist-info/entry_points.txt
cf_util-1.2.1.dist-info/licenses/LICENSE
cf_util-1.2.1.dist-info/RECORD
