Metadata-Version: 2.1
Name: cf_util
Version: 1.2.1
Summary: A python tool to help install accepted submission from codeforces.com.
Project-URL: Homepage, https://github.com/EliasObeid9-02/cf_util
Project-URL: Bug Tracker, https://github.com/EliasObeid9-02/cf_util/issues
Author-email: Elias Obeid <elias.obeid9.02@gmail.com>
Maintainer-email: Elias Obeid <elias.obeid9.02@gmail.com>
License: MIT License
License-File: LICENSE
Classifier: License :: OSI Approved :: MIT License
Classifier: Operating System :: OS Independent
Classifier: Programming Language :: Python :: 3
Requires-Python: >=3.0
Requires-Dist: beautifulsoup4
Requires-Dist: requests
